parsetabtolatex/__init__.py
parsetabtolatex/parsetab.py
parsetabtolatex/parsetabtolatex.py
parsetabtolatex/parsetabtolatex_ast.py
parsetabtolatex/parsetabtolatex_lex.py
parsetabtolatex/parsetabtolatex_yacc.py
parsetabtolatex-0.0.3.dist-info/LICENSE
parsetabtolatex-0.0.3.dist-info/METADATA
parsetabtolatex-0.0.3.dist-info/WHEEL
parsetabtolatex-0.0.3.dist-info/top_level.txt
parsetabtolatex-0.0.3.dist-info/RECORD
