Metadata-Version: 2.1
Name: parsetabtolatex
Version: 0.0.3
Summary: A parsetab.py parser that generates .tex file
Home-page: https://gitlab.climent-pommeret.red/Chopopope/parsetabtolatex/
Author: Maria Climent-Pommeret
Author-email: maria@climent-pommeret.red
License: UNKNOWN
Keywords: ply grammar LaTeX parser
Platform: UNKNOWN
Classifier: Development Status :: 4 - Beta
Classifier: Intended Audience :: Science/Research
Classifier: Programming Language :: Python :: 3
Classifier: License :: OSI Approved :: MIT License
Classifier: Operating System :: OS Independent
Requires-Python: >=3.5
Requires-Dist: ply
